__init__.py
buildpy_server/BuildpyArgumentParser.py
buildpy_server/config.py
buildpy_server/hookspecs.py
buildpy_server/log.py
buildpy_server/main.py
buildpy_server/parseroptions.py
buildpy_server/__init__.py
buildpy_server-0.1.0.dist-info/DESCRIPTION.rst
buildpy_server-0.1.0.dist-info/entry_points.txt
buildpy_server-0.1.0.dist-info/METADATA
buildpy_server-0.1.0.dist-info/metadata.json
buildpy_server-0.1.0.dist-info/pbr.json
buildpy_server-0.1.0.dist-info/RECORD
buildpy_server-0.1.0.dist-info/top_level.txt
buildpy_server-0.1.0.dist-info/WHEEL
