Metadata-Version: 2.0
Name: buildpy-server
Version: 0.1.0
Summary: buildpy-server: reliable local ci server
Home-page: https://github.com/buildpy/buildpy-server
Author: Maik Figura
Author-email: maiksensi@gmail.com
License: MIT
Platform: UNKNOWN
Classifier: Development Status :: 4 - Beta
Classifier: Intended Audience :: Developers
Classifier: Intended Audience :: System Administrators
Classifier: Topic :: Software Development :: Testing
Classifier: Programming Language :: Python
Classifier: Programming Language :: Python :: 3
Classifier: Programming Language :: Python :: 3.4
Classifier: Programming Language :: Python :: Implementation :: CPython
Classifier: Operating System :: OS Independent
Classifier: License :: OSI Approved :: MIT License
Requires-Dist: py (>=1.4.31)
Requires-Dist: pluggy (>=0.3.1)
Requires-Dist: pytest (>=2.8.5)
